MANIFEST.in
README.rst
setup.py
hyde_slimmer/__init__.py
hyde_slimmer/site_post_processors.py
hyde_slimmer.egg-info/PKG-INFO
hyde_slimmer.egg-info/SOURCES.txt
hyde_slimmer.egg-info/dependency_links.txt
hyde_slimmer.egg-info/not-zip-safe
hyde_slimmer.egg-info/requires.txt
hyde_slimmer.egg-info/top_level.txt