Metadata-Version: 1.0
Name: hyde-slimmer
Version: 0.0.1
Summary: Html compression as post processor
Home-page: http://github.com/dstufft/hyde-slimmer
Author: Donald von Stufft
Author-email: donald.stufft@gmail.com
License: BSD
Keywords: hyde html compressor
Platform: UNKNOWN
Classifier: Programming Language :: Python
Classifier: Development Status :: 4 - Beta
Classifier: Intended Audience :: Developers
